{
  "tiles" : [ {
    "scaleFactors" : [ 32, 16, 8, 4, 2, 1 ],
    "width" : 1024,
    "height" : 1024
  } ],
  "protocol" : "http://iiif.io/api/image",
  "sizes" : [ {
    "width" : 253,
    "height" : 182
  }, {
    "width" : 505,
    "height" : 364
  }, {
    "width" : 1010,
    "height" : 727
  }, {
    "width" : 2019,
    "height" : 1454
  }, {
    "width" : 4037,
    "height" : 2907
  }, {
    "width" : 8073,
    "height" : 5813
  } ],
  "profile" : "http://iiif.io/api/image/2/level0.json",
  "width" : 8073,
  "@id" : "https://ksefil.github.io/IIIF_Age_of_Discovery/images/Claudius_Ptolemy",
  "@context" : "http://iiif.io/api/image/2/context.json",
  "height" : 5813
}